{
  "topics_order": [
    {
      "id": "6",
      "name": "AR/VR",
      "enabled": true
    },
    {
      "id": "17",
      "name": "金融财经",
      "enabled": true
    },
    {
      "id": "0",
      "name": "AI大模型",
      "enabled": true
    },
    {
      "id": "3",
      "name": "国内科技公司",
      "enabled": true
    },
    {
      "id": "4",
      "name": "国外科技公司",
      "enabled": true
    },
    {
      "id": "8",
      "name": "航天航空",
      "enabled": true
    },
    {
      "id": "5",
      "name": "芯片半导体",
      "enabled": true
    },
    {
      "id": "7",
      "name": "新能源汽车",
      "enabled": true
    },
    {
      "id": "2",
      "name": "机器人",
      "enabled": true
    },
    {
      "id": "9",
      "name": "大疆无人机",
      "enabled": true
    },
    {
      "id": "1",
      "name": "自动驾驶",
      "enabled": true
    },
    {
      "id": "10",
      "name": "游戏",
      "enabled": true
    },
    {
      "id": "11",
      "name": "科幻影视",
      "enabled": true
    },
    {
      "id": "12",
      "name": "电影",
      "enabled": true
    },
    {
      "id": "16",
      "name": "世界政治",
      "enabled": true
    },
    {
      "id": "14",
      "name": "中国政治",
      "enabled": true
    },
    {
      "id": "15",
      "name": "美国政治",
      "enabled": true
    },
    {
      "id": "13",
      "name": "书籍",
      "enabled": true
    }
  ],
  "ui_tabs": [
    {
      "id": "topics",
      "name": "主题聚合",
      "enabled": true
    },
    {
      "id": "sources",
      "name": "来源聚合",
      "enabled": true
    },
    {
      "id": "newonly",
      "name": "增量新闻",
      "enabled": true
    },
    {
      "id": "report",
      "name": "原始报告",
      "enabled": true
    },
    {
      "id": "nav",
      "name": "主题导航",
      "enabled": true
    },
    {
      "id": "search",
      "name": "搜索",
      "enabled": true
    },
    {
      "id": "filter",
      "name": "筛选",
      "enabled": true
    },
    {
      "id": "allnews",
      "name": "全部新闻",
      "enabled": true
    },
    {
      "id": "settings",
      "name": "设置",
      "enabled": true
    }
  ],
  "platforms": [
    {
      "id": "baidu",
      "name": "百度热搜",
      "enabled": true
    },
    {
      "id": "ifeng",
      "name": "凤凰网",
      "enabled": true
    },
    {
      "id": "toutiao",
      "name": "今日头条",
      "enabled": true
    },
    {
      "id": "thepaper",
      "name": "澎湃新闻",
      "enabled": true
    },
    {
      "id": "cankaoxiaoxi",
      "name": "参考消息",
      "enabled": true
    },
    {
      "id": "sputniknewscn",
      "name": "卫星通讯社",
      "enabled": true
    },
    {
      "id": "zaobao",
      "name": "联合早报",
      "enabled": true
    },
    {
      "id": "mktnews",
      "name": "MKT新闻",
      "enabled": true
    },
    {
      "id": "kaopu",
      "name": "靠谱新闻",
      "enabled": true
    },
    {
      "id": "tencent-hot",
      "name": "腾讯新闻",
      "enabled": true
    },
    {
      "id": "wallstreetcn-hot",
      "name": "华尔街见闻 最热",
      "enabled": true
    },
    {
      "id": "wallstreetcn-quick",
      "name": "华尔街见闻 快讯",
      "enabled": true
    },
    {
      "id": "wallstreetcn-news",
      "name": "华尔街见闻 最新",
      "enabled": true
    },
    {
      "id": "cls-hot",
      "name": "财联社热门",
      "enabled": true
    },
    {
      "id": "cls-telegraph",
      "name": "财联社 电报",
      "enabled": true
    },
    {
      "id": "cls-depth",
      "name": "财联社 深度",
      "enabled": true
    },
    {
      "id": "gelonghui",
      "name": "格隆汇",
      "enabled": true
    },
    {
      "id": "xueqiu",
      "name": "雪球",
      "enabled": true
    },
    {
      "id": "jin10",
      "name": "金十数据",
      "enabled": true
    },
    {
      "id": "fastbull",
      "name": "快讯通",
      "enabled": true
    },
    {
      "id": "fastbull-express",
      "name": "法布财经 快讯",
      "enabled": true
    },
    {
      "id": "fastbull-news",
      "name": "法布财经 头条",
      "enabled": true
    },
    {
      "id": "weibo",
      "name": "微博",
      "enabled": true
    },
    {
      "id": "douyin",
      "name": "抖音",
      "enabled": true
    },
    {
      "id": "kuaishou",
      "name": "快手",
      "enabled": true
    },
    {
      "id": "tieba",
      "name": "贴吧",
      "enabled": true
    },
    {
      "id": "zhihu",
      "name": "知乎",
      "enabled": true
    },
    {
      "id": "hupu",
      "name": "虎扑",
      "enabled": true
    },
    {
      "id": "bilibili-hot-search",
      "name": "bilibili 热搜",
      "enabled": true
    },
    {
      "id": "bilibili-hot-video",
      "name": "bilibili 热门视频",
      "enabled": true
    },
    {
      "id": "bilibili-ranking",
      "name": "bilibili 排行榜",
      "enabled": true
    },
    {
      "id": "qqvideo-tv-hotsearch",
      "name": "腾讯视频 热搜榜",
      "enabled": true
    },
    {
      "id": "iqiyi-hot-ranklist",
      "name": "爱奇艺 热播榜",
      "enabled": true
    },
    {
      "id": "douban",
      "name": "豆瓣",
      "enabled": true
    },
    {
      "id": "ithome",
      "name": "IT之家",
      "enabled": true
    },
    {
      "id": "36kr-quick",
      "name": "36氪 快讯",
      "enabled": true
    },
    {
      "id": "36kr-renqi",
      "name": "36氪 人气榜",
      "enabled": true
    },
    {
      "id": "juejin",
      "name": "掘金",
      "enabled": true
    },
    {
      "id": "github",
      "name": "GitHub",
      "enabled": true
    },
    {
      "id": "hackernews",
      "name": "Hacker News",
      "enabled": true
    },
    {
      "id": "solidot",
      "name": "Solidot",
      "enabled": true
    },
    {
      "id": "v2ex",
      "name": "V2EX",
      "enabled": true
    },
    {
      "id": "nowcoder",
      "name": "牛客网",
      "enabled": true
    },
    {
      "id": "pcbeta",
      "name": "远景论坛",
      "enabled": true
    },
    {
      "id": "sspai",
      "name": "少数派",
      "enabled": true
    },
    {
      "id": "producthunt",
      "name": "ProductHunt",
      "enabled": true
    },
    {
      "id": "coolapk",
      "name": "酷安",
      "enabled": true
    },
    {
      "id": "freebuf",
      "name": "Freebuf 网络安全",
      "enabled": true
    },
    {
      "id": "chongbuluo-hot",
      "name": "虫部落 最热",
      "enabled": true
    },
    {
      "id": "chongbuluo",
      "name": "虫部落 最新",
      "enabled": true
    },
    {
      "id": "steam",
      "name": "Steam 在线人数",
      "enabled": true
    },
    {
      "id": "test",
      "name": "test",
      "enabled": true
    }
  ],
  "rss": {
    "enabled": true,
    "freshness_filter": {
      "enabled": true,
      "max_age_days": 3
    },
    "feeds": [
      {
        "id": "hacker-news",
        "name": "Hacker News",
        "url": "https://hnrss.org/frontpage",
        "category": "tech",
        "enabled": true
      },
      {
        "id": "cnbc",
        "name": "CNBC",
        "url": "https://www.cnbc.com/id/100003114/device/rss/rss.html",
        "category": "finance",
        "enabled": true
      },
      {
        "id": "techcrunch",
        "name": "TechCrunch",
        "url": "https://techcrunch.com/feed/",
        "category": "tech",
        "enabled": true
      },
      {
        "id": "the-verge",
        "name": "The Verge",
        "url": "https://www.theverge.com/rss/index.xml",
        "category": "tech",
        "enabled": true
      },
      {
        "id": "ars-technica",
        "name": "Ars Technica",
        "url": "http://feeds.arstechnica.com/arstechnica/index",
        "category": "tech",
        "enabled": true
      },
      {
        "id": "bbc-news",
        "name": "BBC News",
        "url": "https://feeds.bbci.co.uk/news/rss.xml",
        "category": "news",
        "enabled": true
      },
      {
        "id": "nyt-homepage",
        "name": "纽约时报",
        "url": "https://rss.nytimes.com/services/xml/rss/nyt/HomePage.xml",
        "category": "news",
        "enabled": true
      },
      {
        "id": "ruanyifeng",
        "name": "阮一峰的网络日志",
        "url": "http://www.ruanyifeng.com/blog/atom.xml",
        "category": "community",
        "max_age_days": 7,
        "enabled": true
      },
      {
        "id": "sspai",
        "name": "少数派",
        "url": "https://sspai.com/feed",
        "category": "tech",
        "enabled": true
      },
      {
        "id": "36kr-rss",
        "name": "36氪",
        "url": "https://36kr.com/feed",
        "category": "tech",
        "enabled": true
      },
      {
        "id": "huxiu",
        "name": "虎嗅",
        "url": "https://www.huxiu.com/rss/0.xml",
        "category": "tech",
        "enabled": true
      },
      {
        "id": "ifanr",
        "name": "爱范儿",
        "url": "https://www.ifanr.com/feed",
        "category": "tech",
        "enabled": false
      },
      {
        "id": "geekpark",
        "name": "极客公园",
        "url": "https://www.geekpark.net/rss",
        "category": "tech",
        "enabled": true
      },
      {
        "id": "wallstreetcn-rss",
        "name": "华尔街见闻",
        "url": "https://feedx.net/rss/wallstreetcn.xml",
        "category": "finance",
        "enabled": true
      },
      {
        "id": "caixin",
        "name": "财新网",
        "url": "https://feedx.net/rss/caixin.xml",
        "category": "finance",
        "enabled": true
      },
      {
        "id": "thepaper-rss",
        "name": "澎湃新闻",
        "url": "https://feedx.net/rss/thepaper.xml",
        "category": "news",
        "enabled": true
      },
      {
        "id": "initium",
        "name": "端传媒",
        "url": "https://theinitium.com/newsfeed/",
        "category": "news",
        "enabled": true
      },
      {
        "id": "nyt-cn",
        "name": "纽约时报中文网",
        "url": "https://cn.nytimes.com/rss/",
        "category": "news",
        "enabled": true
      },
      {
        "id": "coolshell",
        "name": "酷壳",
        "url": "https://coolshell.cn/feed",
        "category": "community",
        "max_age_days": 30,
        "enabled": true
      },
      {
        "id": "zhihu-daily",
        "name": "知乎每日精选",
        "url": "https://www.zhihu.com/rss",
        "category": "community",
        "enabled": true
      },
      {
        "id": "v2ex-rss",
        "name": "V2EX",
        "url": "https://www.v2ex.com/index.xml",
        "category": "community",
        "enabled": true
      }
    ]
  }
}